bandcamp_list_albums.py
bandcamp_list_albums-0.0.4.dist-info/LICENSE
bandcamp_list_albums-0.0.4.dist-info/METADATA
bandcamp_list_albums-0.0.4.dist-info/WHEEL
bandcamp_list_albums-0.0.4.dist-info/entry_points.txt
bandcamp_list_albums-0.0.4.dist-info/top_level.txt
bandcamp_list_albums-0.0.4.dist-info/RECORD
