Metadata-Version: 2.1
Name: bandcamp-list-albums
Version: 0.0.4
Summary: List albums from bandcamp page of artist or label.
Home-page: https://github.com/Layerex/bandcamp_list_albums
Author: Layerex
Author-email: layerex@dismail.de
License: UNKNOWN
Platform: UNKNOWN
Classifier: Development Status :: 6 - Mature
Classifier: Programming Language :: Python :: 3
Classifier: License :: OSI Approved :: GNU General Public License v3 (GPLv3)
Classifier: Operating System :: OS Independent
Classifier: Topic :: Utilities
License-File: LICENSE
Requires-Dist: beautifulsoup4
Requires-Dist: requests
